applp/__init__.py
applp/modules/__init__.py
applp/py.typed
applp/routines/__init__.py
applp-0.1.10.dist-info/WHEEL
applp-0.1.10.dist-info/METADATA
applp-0.1.10.dist-info/RECORD
