Metadata-Version: 2.3
Name: applp
Version: 0.1.10
Summary: A library for custom GUI interface creation.
Requires-Dist: corelp
Requires-Python: >=3.12
